kestrel_ipython/__init__.py
kestrel_ipython/magic.py
kestrel_jupyter_kernel/__init__.py
kestrel_jupyter_kernel/__main__.py
kestrel_jupyter_kernel/config.py
kestrel_jupyter_kernel/kernel.py
kestrel_jupyter_kernel/logo-64x64.png
kestrel_jupyter_kernel/setup.py
kestrel_jupyter_kernel/codemirror/__init__.py
kestrel_jupyter_kernel/codemirror/kestrel_template.js
kestrel_jupyter_kernel/codemirror/setup.py
kestrel_jupyter-1.8.7.dist-info/METADATA
kestrel_jupyter-1.8.7.dist-info/WHEEL
kestrel_jupyter-1.8.7.dist-info/entry_points.txt
kestrel_jupyter-1.8.7.dist-info/top_level.txt
kestrel_jupyter-1.8.7.dist-info/RECORD
