Metadata-Version: 2.1
Name: kestrel_jupyter
Version: 1.8.7
Summary: Kestrel Jupyter Kernel
Maintainer-email: Xiaokui Shu <xiaokui.shu@ibm.com>, Paul Coccoli <pcoccoli@us.ibm.com>
License: Apache 2.0 License
Project-URL: Homepage, https://github.com/opencybersecurityalliance/kestrel-lang
Project-URL: Documentation, https://kestrel.readthedocs.io/
Project-URL: Repository, https://github.com/opencybersecurityalliance/kestrel-lang.git
Keywords: kestrel,Jupyter,kernel
Classifier: Topic :: Security
Classifier: Operating System :: OS Independent
Classifier: Development Status :: 4 - Beta
Classifier: Programming Language :: Python :: 3
Requires-Python: >=3.8
Requires-Dist: kestrel_core==1.8.2
Requires-Dist: kestrel_datasource_stixbundle==1.8.0
Requires-Dist: kestrel_datasource_stixshifter==1.8.5
Requires-Dist: kestrel_analytics_python==1.8.0
Requires-Dist: kestrel_analytics_docker==1.8.1
Requires-Dist: jupyterlab-server
Requires-Dist: jupyterlab
Requires-Dist: jupyter_client
Requires-Dist: nbclassic
Provides-Extra: test
Requires-Dist: pytest; extra == "test"
